gadgetpie/__init__.py
gadgetpie/dict2class.py
gadgetpie/logger.py
gadgetpie-0.0.1.dist-info/LICENSE
gadgetpie-0.0.1.dist-info/METADATA
gadgetpie-0.0.1.dist-info/WHEEL
gadgetpie-0.0.1.dist-info/top_level.txt
gadgetpie-0.0.1.dist-info/RECORD
