Metadata-Version: 2.1
Name: gadgetpie
Version: 0.0.1
Summary: A set of common tools.
Home-page: https://github.com/Baoming520/gadgetpie
Author: Baoming Yu
Author-email: dingxuanliang@icloud.com
License-File: LICENSE
